incstatspy.cpython-38-x86_64-linux-gnu.so
lib64/libincstats.so
lib64/cmake/incstats/incstatsConfig.cmake
lib64/cmake/incstats/incstatsConfig-release.cmake
incstatspy-0.3.2.dist-info/METADATA
incstatspy-0.3.2.dist-info/RECORD
incstatspy-0.3.2.dist-info/WHEEL
incstatspy-0.3.2.dist-info/licenses/LICENSE.txt
include/incstats.h
