Metadata-Version: 2.1
Name: incstatspy
Version: 0.3.2
